{
    "name": "Product search",
    "description": "Advanced collector for products",
    "layout": {
        "groups": [
            {
                "sections": [
                    {
                        "rows": [
                            {
                                "columns": [
                                    {
                                        "width": "100%",
                                        "items": [
                                            {
                                                "type": "field",
                                                "label": "Is Internal",
                                                "value": "is_internal",
                                                "width": "20%"
                                            },
                                            {
                                                "type": "field",
                                                "value": "customer_id",
                                                "label": "Customer",
                                                "width": "20%"
                                            }
                                        ]
                                    },
                                    {
                                        "width": "100%",
                                        "items": [
                                            {
                                                "type": "field",
                                                "value": "server_id",
                                                "label": "Server",
                                                "width": "20%"
                                            },
                                            {
                                                "type": "field",
                                                "value": "service_id",
                                                "label": "Service",
                                                "width": "20%"
                                            }
                                        ]
                                    }
                                ]
                            }
                        ]
                    }
                ]
            }
        ]
    }
}